hostfact_python_client/__init__.py
hostfact_python_client/hostfact_client.py
hostfact_python_client/utilities.py
hostfact_python_client-0.1.10.dist-info/METADATA
hostfact_python_client-0.1.10.dist-info/WHEEL
hostfact_python_client-0.1.10.dist-info/RECORD
