Metadata-Version: 2.1
Name: hostfact-python-client
Version: 0.1.10
Summary: 
Author: Kamenlom
Author-email: ivashchenko.roman111@gmail.com
Requires-Python: >=3.11,<4.0
Classifier: Programming Language :: Python :: 3
Classifier: Programming Language :: Python :: 3.11
Classifier: Programming Language :: Python :: 3.12
Requires-Dist: httpx (>=0.27,<0.28)
Requires-Dist: requests (>=2.25.1,<3.0.0)
Requires-Dist: respx (>=0.20,<0.21)
Requires-Dist: vcrpy (>=4.1.1,<5.0.0)
